[
	{
		"file": "E:\\project\\UE\\demo0705\\Source\\Test_GamePlay\\Common\\AttackAreaBase.cpp",
		"arguments": [
			"E:\\tool\\vs2022\\build tool\\VC\\Tools\\MSVC\\14.44.35207\\bin\\Hostx64\\x64\\cl.exe",
			"@E:\\project\\UE\\demo0705\\.vscode\\compileCommands_Default\\Test_GamePlay.0.rsp"
		],
		"directory": "E:\\tool\\epic\\UE_5.8\\Engine\\Source"
	},
	{
		"file": "E:\\project\\UE\\demo0705\\Source\\Test_GamePlay\\Common\\StateBase.cpp",
		"arguments": [
			"E:\\tool\\vs2022\\build tool\\VC\\Tools\\MSVC\\14.44.35207\\bin\\Hostx64\\x64\\cl.exe",
			"@E:\\project\\UE\\demo0705\\.vscode\\compileCommands_Default\\Test_GamePlay.0.rsp"
		],
		"directory": "E:\\tool\\epic\\UE_5.8\\Engine\\Source"
	},
	{
		"file": "E:\\project\\UE\\demo0705\\Source\\Test_GamePlay\\Enemy\\EnemyBase.cpp",
		"arguments": [
			"E:\\tool\\vs2022\\build tool\\VC\\Tools\\MSVC\\14.44.35207\\bin\\Hostx64\\x64\\cl.exe",
			"@E:\\project\\UE\\demo0705\\.vscode\\compileCommands_Default\\Test_GamePlay.0.rsp"
		],
		"directory": "E:\\tool\\epic\\UE_5.8\\Engine\\Source"
	},
	{
		"file": "E:\\project\\UE\\demo0705\\Source\\Test_GamePlay\\HikariPlayerCharacter.cpp",
		"arguments": [
			"E:\\tool\\vs2022\\build tool\\VC\\Tools\\MSVC\\14.44.35207\\bin\\Hostx64\\x64\\cl.exe",
			"@E:\\project\\UE\\demo0705\\.vscode\\compileCommands_Default\\Test_GamePlay.0.rsp"
		],
		"directory": "E:\\tool\\epic\\UE_5.8\\Engine\\Source"
	},
	{
		"file": "E:\\project\\UE\\demo0705\\Source\\Test_GamePlay\\Room\\DemoRoomManager.cpp",
		"arguments": [
			"E:\\tool\\vs2022\\build tool\\VC\\Tools\\MSVC\\14.44.35207\\bin\\Hostx64\\x64\\cl.exe",
			"@E:\\project\\UE\\demo0705\\.vscode\\compileCommands_Default\\Test_GamePlay.0.rsp"
		],
		"directory": "E:\\tool\\epic\\UE_5.8\\Engine\\Source"
	},
	{
		"file": "E:\\project\\UE\\demo0705\\Source\\Test_GamePlay\\Room\\EnemySpawnPoint.cpp",
		"arguments": [
			"E:\\tool\\vs2022\\build tool\\VC\\Tools\\MSVC\\14.44.35207\\bin\\Hostx64\\x64\\cl.exe",
			"@E:\\project\\UE\\demo0705\\.vscode\\compileCommands_Default\\Test_GamePlay.0.rsp"
		],
		"directory": "E:\\tool\\epic\\UE_5.8\\Engine\\Source"
	},
	{
		"file": "E:\\project\\UE\\demo0705\\Source\\Test_GamePlay\\Skill\\HikariSkillComponent.cpp",
		"arguments": [
			"E:\\tool\\vs2022\\build tool\\VC\\Tools\\MSVC\\14.44.35207\\bin\\Hostx64\\x64\\cl.exe",
			"@E:\\project\\UE\\demo0705\\.vscode\\compileCommands_Default\\Test_GamePlay.0.rsp"
		],
		"directory": "E:\\tool\\epic\\UE_5.8\\Engine\\Source"
	},
	{
		"file": "E:\\project\\UE\\demo0705\\Source\\Test_GamePlay\\Skill\\SkillCircleDamageArea.cpp",
		"arguments": [
			"E:\\tool\\vs2022\\build tool\\VC\\Tools\\MSVC\\14.44.35207\\bin\\Hostx64\\x64\\cl.exe",
			"@E:\\project\\UE\\demo0705\\.vscode\\compileCommands_Default\\Test_GamePlay.0.rsp"
		],
		"directory": "E:\\tool\\epic\\UE_5.8\\Engine\\Source"
	},
	{
		"file": "E:\\project\\UE\\demo0705\\Source\\Test_GamePlay\\Test_GamePlay.cpp",
		"arguments": [
			"E:\\tool\\vs2022\\build tool\\VC\\Tools\\MSVC\\14.44.35207\\bin\\Hostx64\\x64\\cl.exe",
			"@E:\\project\\UE\\demo0705\\.vscode\\compileCommands_Default\\Test_GamePlay.0.rsp"
		],
		"directory": "E:\\tool\\epic\\UE_5.8\\Engine\\Source"
	},
	{
		"file": "E:\\project\\UE\\demo0705\\Source\\Test_GamePlay\\Test_GamePlayCharacter.cpp",
		"arguments": [
			"E:\\tool\\vs2022\\build tool\\VC\\Tools\\MSVC\\14.44.35207\\bin\\Hostx64\\x64\\cl.exe",
			"@E:\\project\\UE\\demo0705\\.vscode\\compileCommands_Default\\Test_GamePlay.0.rsp"
		],
		"directory": "E:\\tool\\epic\\UE_5.8\\Engine\\Source"
	},
	{
		"file": "E:\\project\\UE\\demo0705\\Source\\Test_GamePlay\\Test_GamePlayGameMode.cpp",
		"arguments": [
			"E:\\tool\\vs2022\\build tool\\VC\\Tools\\MSVC\\14.44.35207\\bin\\Hostx64\\x64\\cl.exe",
			"@E:\\project\\UE\\demo0705\\.vscode\\compileCommands_Default\\Test_GamePlay.0.rsp"
		],
		"directory": "E:\\tool\\epic\\UE_5.8\\Engine\\Source"
	},
	{
		"file": "E:\\project\\UE\\demo0705\\Source\\Test_GamePlay\\Test_GamePlayPlayerController.cpp",
		"arguments": [
			"E:\\tool\\vs2022\\build tool\\VC\\Tools\\MSVC\\14.44.35207\\bin\\Hostx64\\x64\\cl.exe",
			"@E:\\project\\UE\\demo0705\\.vscode\\compileCommands_Default\\Test_GamePlay.0.rsp"
		],
		"directory": "E:\\tool\\epic\\UE_5.8\\Engine\\Source"
	},
	{
		"file": "E:\\project\\UE\\demo0705\\Source\\Test_GamePlay\\Variant_Strategy\\EnvQueryContext_MoveGoal.cpp",
		"arguments": [
			"E:\\tool\\vs2022\\build tool\\VC\\Tools\\MSVC\\14.44.35207\\bin\\Hostx64\\x64\\cl.exe",
			"@E:\\project\\UE\\demo0705\\.vscode\\compileCommands_Default\\Test_GamePlay.0.rsp"
		],
		"directory": "E:\\tool\\epic\\UE_5.8\\Engine\\Source"
	},
	{
		"file": "E:\\project\\UE\\demo0705\\Source\\Test_GamePlay\\Variant_Strategy\\StrategyGameMode.cpp",
		"arguments": [
			"E:\\tool\\vs2022\\build tool\\VC\\Tools\\MSVC\\14.44.35207\\bin\\Hostx64\\x64\\cl.exe",
			"@E:\\project\\UE\\demo0705\\.vscode\\compileCommands_Default\\Test_GamePlay.0.rsp"
		],
		"directory": "E:\\tool\\epic\\UE_5.8\\Engine\\Source"
	},
	{
		"file": "E:\\project\\UE\\demo0705\\Source\\Test_GamePlay\\Variant_Strategy\\StrategyPawn.cpp",
		"arguments": [
			"E:\\tool\\vs2022\\build tool\\VC\\Tools\\MSVC\\14.44.35207\\bin\\Hostx64\\x64\\cl.exe",
			"@E:\\project\\UE\\demo0705\\.vscode\\compileCommands_Default\\Test_GamePlay.0.rsp"
		],
		"directory": "E:\\tool\\epic\\UE_5.8\\Engine\\Source"
	},
	{
		"file": "E:\\project\\UE\\demo0705\\Source\\Test_GamePlay\\Variant_Strategy\\StrategyPlayerController.cpp",
		"arguments": [
			"E:\\tool\\vs2022\\build tool\\VC\\Tools\\MSVC\\14.44.35207\\bin\\Hostx64\\x64\\cl.exe",
			"@E:\\project\\UE\\demo0705\\.vscode\\compileCommands_Default\\Test_GamePlay.0.rsp"
		],
		"directory": "E:\\tool\\epic\\UE_5.8\\Engine\\Source"
	},
	{
		"file": "E:\\project\\UE\\demo0705\\Source\\Test_GamePlay\\Variant_Strategy\\StrategyUnit.cpp",
		"arguments": [
			"E:\\tool\\vs2022\\build tool\\VC\\Tools\\MSVC\\14.44.35207\\bin\\Hostx64\\x64\\cl.exe",
			"@E:\\project\\UE\\demo0705\\.vscode\\compileCommands_Default\\Test_GamePlay.0.rsp"
		],
		"directory": "E:\\tool\\epic\\UE_5.8\\Engine\\Source"
	},
	{
		"file": "E:\\project\\UE\\demo0705\\Source\\Test_GamePlay\\Variant_Strategy\\UI\\StrategyHUD.cpp",
		"arguments": [
			"E:\\tool\\vs2022\\build tool\\VC\\Tools\\MSVC\\14.44.35207\\bin\\Hostx64\\x64\\cl.exe",
			"@E:\\project\\UE\\demo0705\\.vscode\\compileCommands_Default\\Test_GamePlay.0.rsp"
		],
		"directory": "E:\\tool\\epic\\UE_5.8\\Engine\\Source"
	},
	{
		"file": "E:\\project\\UE\\demo0705\\Source\\Test_GamePlay\\Variant_Strategy\\UI\\StrategyTouchControls.cpp",
		"arguments": [
			"E:\\tool\\vs2022\\build tool\\VC\\Tools\\MSVC\\14.44.35207\\bin\\Hostx64\\x64\\cl.exe",
			"@E:\\project\\UE\\demo0705\\.vscode\\compileCommands_Default\\Test_GamePlay.0.rsp"
		],
		"directory": "E:\\tool\\epic\\UE_5.8\\Engine\\Source"
	},
	{
		"file": "E:\\project\\UE\\demo0705\\Source\\Test_GamePlay\\Variant_Strategy\\UI\\StrategyUI.cpp",
		"arguments": [
			"E:\\tool\\vs2022\\build tool\\VC\\Tools\\MSVC\\14.44.35207\\bin\\Hostx64\\x64\\cl.exe",
			"@E:\\project\\UE\\demo0705\\.vscode\\compileCommands_Default\\Test_GamePlay.0.rsp"
		],
		"directory": "E:\\tool\\epic\\UE_5.8\\Engine\\Source"
	},
	{
		"file": "E:\\project\\UE\\demo0705\\Source\\Test_GamePlay\\Variant_TwinStick\\AI\\TwinStickAIController.cpp",
		"arguments": [
			"E:\\tool\\vs2022\\build tool\\VC\\Tools\\MSVC\\14.44.35207\\bin\\Hostx64\\x64\\cl.exe",
			"@E:\\project\\UE\\demo0705\\.vscode\\compileCommands_Default\\Test_GamePlay.0.rsp"
		],
		"directory": "E:\\tool\\epic\\UE_5.8\\Engine\\Source"
	},
	{
		"file": "E:\\project\\UE\\demo0705\\Source\\Test_GamePlay\\Variant_TwinStick\\AI\\TwinStickNPC.cpp",
		"arguments": [
			"E:\\tool\\vs2022\\build tool\\VC\\Tools\\MSVC\\14.44.35207\\bin\\Hostx64\\x64\\cl.exe",
			"@E:\\project\\UE\\demo0705\\.vscode\\compileCommands_Default\\Test_GamePlay.0.rsp"
		],
		"directory": "E:\\tool\\epic\\UE_5.8\\Engine\\Source"
	},
	{
		"file": "E:\\project\\UE\\demo0705\\Source\\Test_GamePlay\\Variant_TwinStick\\AI\\TwinStickNPCDestruction.cpp",
		"arguments": [
			"E:\\tool\\vs2022\\build tool\\VC\\Tools\\MSVC\\14.44.35207\\bin\\Hostx64\\x64\\cl.exe",
			"@E:\\project\\UE\\demo0705\\.vscode\\compileCommands_Default\\Test_GamePlay.0.rsp"
		],
		"directory": "E:\\tool\\epic\\UE_5.8\\Engine\\Source"
	},
	{
		"file": "E:\\project\\UE\\demo0705\\Source\\Test_GamePlay\\Variant_TwinStick\\AI\\TwinStickSpawner.cpp",
		"arguments": [
			"E:\\tool\\vs2022\\build tool\\VC\\Tools\\MSVC\\14.44.35207\\bin\\Hostx64\\x64\\cl.exe",
			"@E:\\project\\UE\\demo0705\\.vscode\\compileCommands_Default\\Test_GamePlay.0.rsp"
		],
		"directory": "E:\\tool\\epic\\UE_5.8\\Engine\\Source"
	},
	{
		"file": "E:\\project\\UE\\demo0705\\Source\\Test_GamePlay\\Variant_TwinStick\\AI\\TwinStickStateTreeUtility.cpp",
		"arguments": [
			"E:\\tool\\vs2022\\build tool\\VC\\Tools\\MSVC\\14.44.35207\\bin\\Hostx64\\x64\\cl.exe",
			"@E:\\project\\UE\\demo0705\\.vscode\\compileCommands_Default\\Test_GamePlay.0.rsp"
		],
		"directory": "E:\\tool\\epic\\UE_5.8\\Engine\\Source"
	},
	{
		"file": "E:\\project\\UE\\demo0705\\Source\\Test_GamePlay\\Variant_TwinStick\\Gameplay\\TwinStickAoEAttack.cpp",
		"arguments": [
			"E:\\tool\\vs2022\\build tool\\VC\\Tools\\MSVC\\14.44.35207\\bin\\Hostx64\\x64\\cl.exe",
			"@E:\\project\\UE\\demo0705\\.vscode\\compileCommands_Default\\Test_GamePlay.0.rsp"
		],
		"directory": "E:\\tool\\epic\\UE_5.8\\Engine\\Source"
	},
	{
		"file": "E:\\project\\UE\\demo0705\\Source\\Test_GamePlay\\Variant_TwinStick\\Gameplay\\TwinStickPickup.cpp",
		"arguments": [
			"E:\\tool\\vs2022\\build tool\\VC\\Tools\\MSVC\\14.44.35207\\bin\\Hostx64\\x64\\cl.exe",
			"@E:\\project\\UE\\demo0705\\.vscode\\compileCommands_Default\\Test_GamePlay.0.rsp"
		],
		"directory": "E:\\tool\\epic\\UE_5.8\\Engine\\Source"
	},
	{
		"file": "E:\\project\\UE\\demo0705\\Source\\Test_GamePlay\\Variant_TwinStick\\Gameplay\\TwinStickProjectile.cpp",
		"arguments": [
			"E:\\tool\\vs2022\\build tool\\VC\\Tools\\MSVC\\14.44.35207\\bin\\Hostx64\\x64\\cl.exe",
			"@E:\\project\\UE\\demo0705\\.vscode\\compileCommands_Default\\Test_GamePlay.0.rsp"
		],
		"directory": "E:\\tool\\epic\\UE_5.8\\Engine\\Source"
	},
	{
		"file": "E:\\project\\UE\\demo0705\\Source\\Test_GamePlay\\Variant_TwinStick\\TwinStickCharacter.cpp",
		"arguments": [
			"E:\\tool\\vs2022\\build tool\\VC\\Tools\\MSVC\\14.44.35207\\bin\\Hostx64\\x64\\cl.exe",
			"@E:\\project\\UE\\demo0705\\.vscode\\compileCommands_Default\\Test_GamePlay.0.rsp"
		],
		"directory": "E:\\tool\\epic\\UE_5.8\\Engine\\Source"
	},
	{
		"file": "E:\\project\\UE\\demo0705\\Source\\Test_GamePlay\\Variant_TwinStick\\TwinStickGameMode.cpp",
		"arguments": [
			"E:\\tool\\vs2022\\build tool\\VC\\Tools\\MSVC\\14.44.35207\\bin\\Hostx64\\x64\\cl.exe",
			"@E:\\project\\UE\\demo0705\\.vscode\\compileCommands_Default\\Test_GamePlay.0.rsp"
		],
		"directory": "E:\\tool\\epic\\UE_5.8\\Engine\\Source"
	},
	{
		"file": "E:\\project\\UE\\demo0705\\Source\\Test_GamePlay\\Variant_TwinStick\\TwinStickPlayerController.cpp",
		"arguments": [
			"E:\\tool\\vs2022\\build tool\\VC\\Tools\\MSVC\\14.44.35207\\bin\\Hostx64\\x64\\cl.exe",
			"@E:\\project\\UE\\demo0705\\.vscode\\compileCommands_Default\\Test_GamePlay.0.rsp"
		],
		"directory": "E:\\tool\\epic\\UE_5.8\\Engine\\Source"
	},
	{
		"file": "E:\\project\\UE\\demo0705\\Source\\Test_GamePlay\\Variant_TwinStick\\UI\\TwinStickUI.cpp",
		"arguments": [
			"E:\\tool\\vs2022\\build tool\\VC\\Tools\\MSVC\\14.44.35207\\bin\\Hostx64\\x64\\cl.exe",
			"@E:\\project\\UE\\demo0705\\.vscode\\compileCommands_Default\\Test_GamePlay.0.rsp"
		],
		"directory": "E:\\tool\\epic\\UE_5.8\\Engine\\Source"
	}
]